{
  "json": {
    "cherrikka/manifest.json": [
      "createdAt"
    ],
    "data.json": [
      "time",
      "indexedDB.message_blocks[].id",
      "indexedDB.message_blocks[].createdAt",
      "indexedDB.message_blocks[].toolId",
      "indexedDB.topics[].messages[].createdAt",
      "indexedDB.topics[].messages[].blocks[]"
    ]
  },
  "sqlite": {
    "rikka_hub.db": {
      "ignoreColumns": {
        "ConversationEntity": [
          "create_at",
          "update_at"
        ],
        "managed_files": [
          "created_at",
          "updated_at"
        ],
        "message_node": [
          "id"
        ]
      },
      "stripMessageFields": [
        "id"
      ]
    }
  }
}
